odoo/addons/product_state_active/README.rst
odoo/addons/product_state_active/__init__.py
odoo/addons/product_state_active/__manifest__.py
odoo/addons/product_state_active/i18n/es.po
odoo/addons/product_state_active/i18n/it.po
odoo/addons/product_state_active/i18n/product_state_active.pot
odoo/addons/product_state_active/models/__init__.py
odoo/addons/product_state_active/models/product_state.py
odoo/addons/product_state_active/models/product_template.py
odoo/addons/product_state_active/readme/CONTRIBUTORS.rst
odoo/addons/product_state_active/readme/DESCRIPTION.rst
odoo/addons/product_state_active/readme/USAGE.rst
odoo/addons/product_state_active/static/description/icon.png
odoo/addons/product_state_active/static/description/index.html
odoo/addons/product_state_active/tests/__init__.py
odoo/addons/product_state_active/tests/test_product_state.py
odoo/addons/product_state_active/views/product_state.xml
odoo14_addon_product_state_active-14.0.1.0.1.dev7.dist-info/METADATA
odoo14_addon_product_state_active-14.0.1.0.1.dev7.dist-info/WHEEL
odoo14_addon_product_state_active-14.0.1.0.1.dev7.dist-info/top_level.txt
odoo14_addon_product_state_active-14.0.1.0.1.dev7.dist-info/RECORD
